jobbee/__init__.py
jobbee/jobbee.py
jobbee-0.0.1.dist-info/LICENSE
jobbee-0.0.1.dist-info/METADATA
jobbee-0.0.1.dist-info/WHEEL
jobbee-0.0.1.dist-info/top_level.txt
jobbee-0.0.1.dist-info/RECORD
