Metadata-Version: 2.1
Name: jobbee
Version: 0.0.1
Summary: Job Bee Python interaction library
Home-page: https://jobbee.readthedocs.io/
Author: Richard Vaughan
Author-email: Richard Vaughan <richard@purplemonkeys.co.uk>
License: MIT
Project-URL: Homepage, https://github.com/pmc-jobbee/python
Project-URL: Bug Tracker, https://github.com/pmc-jobbee/python/issues
Classifier: Programming Language :: Python :: 3
Classifier: License :: OSI Approved :: MIT License
Classifier: Operating System :: OS Independent
Requires-Python: >=3.6
License-File: LICENSE
